{
  "annotations": {
    "changelogDate": "20250826060113"
  },
  "applications": "*",
  "dto": "mapstruct",
  "fields": [
    {
      "fieldName": "id",
      "fieldType": "Long"
    },
    {
      "fieldName": "firstName",
      "fieldType": "String",
      "fieldValidateRules": ["required"]
    },
    {
      "fieldName": "lastName",
      "fieldType": "String",
      "fieldValidateRules": ["required"]
    },
    {
      "fieldName": "title",
      "fieldType": "String",
      "fieldValidateRules": ["required"]
    },
    {
      "fieldName": "designation",
      "fieldType": "String"
    },
    {
      "fieldName": "bio",
      "fieldType": "String",
      "fieldValidateRules": ["maxlength"],
      "fieldValidateRulesMaxlength": "2048"
    },
    {
      "fieldName": "email",
      "fieldType": "String"
    },
    {
      "fieldName": "profileImageUrl",
      "fieldType": "String"
    },
    {
      "fieldName": "expertise",
      "fieldType": "String",
      "fieldValidateRules": ["maxlength"],
      "fieldValidateRulesMaxlength": "4096"
    },
    {
      "fieldName": "imageBackground",
      "fieldType": "String"
    },
    {
      "fieldName": "imageStyle",
      "fieldType": "String"
    },
    {
      "fieldName": "department",
      "fieldType": "String"
    },
    {
      "fieldName": "joinDate",
      "fieldType": "LocalDate"
    },
    {
      "fieldName": "isActive",
      "fieldType": "Boolean"
    },
    {
      "fieldName": "linkedinUrl",
      "fieldType": "String"
    },
    {
      "fieldName": "twitterUrl",
      "fieldType": "String"
    },
    {
      "fieldName": "priorityOrder",
      "fieldType": "Integer"
    },
    {
      "fieldName": "websiteUrl",
      "fieldType": "String"
    }
  ],
  "jpaMetamodelFiltering": true,
  "microserviceName": "eventmanagement",
  "name": "ExecutiveCommitteeTeamMember",
  "pagination": "pagination",
  "relationships": [],
  "searchEngine": "no",
  "service": "serviceImpl"
}
